ayugespidertools/__init__.py
ayugespidertools/commands/__init__.py
ayugespidertools/commands/crawl.py
ayugespidertools/commands/genspider.py
ayugespidertools/commands/startproject.py
ayugespidertools/commands/version.py
ayugespidertools/common/__init__.py
ayugespidertools/common/confighandler.py
ayugespidertools/common/encryption.py
ayugespidertools/common/expend.py
ayugespidertools/common/mongodbpipe.py
ayugespidertools/common/multiplexing.py
ayugespidertools/common/mysqlerrhandle.py
ayugespidertools/common/params.py
ayugespidertools/common/postgreserrhandle.py
ayugespidertools/common/spiderconf.py
ayugespidertools/common/sqlformat.py
ayugespidertools/common/typevars.py
ayugespidertools/common/utils.py
ayugespidertools/config.py
ayugespidertools/data/browsers.json
ayugespidertools/exceptions.py
ayugespidertools/extras/__init__.py
ayugespidertools/extras/cvnpil.py
ayugespidertools/extras/deduplicate.py
ayugespidertools/extras/ext.py
ayugespidertools/extras/oss.py
ayugespidertools/formatdata.py
ayugespidertools/items.py
ayugespidertools/middlewares.py
ayugespidertools/mongoclient.py
ayugespidertools/mysqlclient.py
ayugespidertools/pipelines.py
ayugespidertools/request.py
ayugespidertools/scraper/__init__.py
ayugespidertools/scraper/http/__init__.py
ayugespidertools/scraper/http/request/__init__.py
ayugespidertools/scraper/http/request/aiohttp.py
ayugespidertools/scraper/middlewares/__init__.py
ayugespidertools/scraper/middlewares/headers/__init__.py
ayugespidertools/scraper/middlewares/headers/ua.py
ayugespidertools/scraper/middlewares/netlib/__init__.py
ayugespidertools/scraper/middlewares/netlib/aiohttplib.py
ayugespidertools/scraper/middlewares/proxy/__init__.py
ayugespidertools/scraper/middlewares/proxy/default.py
ayugespidertools/scraper/pipelines/__init__.py
ayugespidertools/scraper/pipelines/download/__init__.py
ayugespidertools/scraper/pipelines/download/file.py
ayugespidertools/scraper/pipelines/es/__init__.py
ayugespidertools-3.14.0.dist-info/LICENSE
ayugespidertools-3.14.0.dist-info/METADATA
ayugespidertools-3.14.0.dist-info/WHEEL
ayugespidertools-3.14.0.dist-info/entry_points.txt
ayugespidertools-3.14.0.dist-info/RECORD
