Metadata-Version: 2.3
Name: AyugeSpiderTools
Version: 3.14.0
Summary: scrapy 扩展库：用于扩展 Scrapy 功能来解放双手。
License: MIT
Keywords: crawler,scraping,scrapy-extension
Author: ayuge
Author-email: ayugesheng@gmail.com
Maintainer: ayuge
Maintainer-email: ayugesheng@gmail.com
Requires-Python: >=3.10
Classifier: License :: OSI Approved :: MIT License
Classifier: Programming Language :: Python :: 3
Classifier: Programming Language :: Python :: 3.10
Classifier: Programming Language :: Python :: 3.11
Classifier: Programming Language :: Python :: 3.12
Classifier: Programming Language :: Python :: 3.13
Provides-Extra: all
Provides-Extra: database
Requires-Dist: aio-pika (>=9.5.5,<9.6.0) ; extra == "all"
Requires-Dist: aio-pika (>=9.5.5,<9.6.0) ; extra == "database"
Requires-Dist: aiohttp (>=3.13.1,<3.14.0)
Requires-Dist: aiomysql (>=0.3.0,<0.4.0)
Requires-Dist: asyncpg (>=0.31.0,<0.32.0) ; extra == "all"
Requires-Dist: asyncpg (>=0.31.0,<0.32.0) ; extra == "database"
Requires-Dist: dbutils (>=3.1.1,<4.0.0)
Requires-Dist: elasticsearch-dsl (>=8.16.0,<9.0.0) ; extra == "all"
Requires-Dist: elasticsearch-dsl (>=8.16.0,<9.0.0) ; extra == "database"
Requires-Dist: itemadapter (>=0.13.0,<0.14.0)
Requires-Dist: kafka-python (>=2.3.0,<2.4.0)
Requires-Dist: loguru (>=0.7.3,<0.8.0)
Requires-Dist: mmh3 (>=5.2.0,<6.0.0) ; extra == "all"
Requires-Dist: motor (>=3.7.0,<3.8.0)
Requires-Dist: numpy (>=2.2.6,<3.0.0) ; extra == "all"
Requires-Dist: opencv-python (>=4.13.0.90,<4.14.0.0) ; extra == "all"
Requires-Dist: oracledb (>=3.4.0,<4.0.0) ; extra == "all"
Requires-Dist: oracledb (>=3.4.0,<4.0.0) ; extra == "database"
Requires-Dist: oss2 (>=2.19.1,<3.0.0) ; extra == "all"
Requires-Dist: pika (>=1.3.2,<1.4.0)
Requires-Dist: psycopg[binary,pool] (>=3.3.0,<3.4.0) ; extra == "all"
Requires-Dist: psycopg[binary,pool] (>=3.3.0,<3.4.0) ; extra == "database"
Requires-Dist: pycryptodome (>=3.23.0,<4.0.0) ; extra == "all"
Requires-Dist: pymysql (>=1.1.1,<2.0.0)
Requires-Dist: python-hcl2 (>=7.3.0,<8.0.0) ; extra == "all"
Requires-Dist: pyyaml (>=6.0,<6.1) ; extra == "all"
Requires-Dist: redis (>=7.1.0,<7.2.0) ; extra == "all"
Requires-Dist: redis (>=7.1.0,<7.2.0) ; extra == "database"
Requires-Dist: scrapy (==2.14.1)
Project-URL: Documentation, https://ayugespidertools.readthedocs.io/en/latest/
Project-URL: Homepage, https://www.ayuge.top/mkdocs-material/
Project-URL: Repository, https://github.com/shengchenyang/AyugeSpiderTools
